{
  "dependencies": {
    "apis1": {
      "resourceId": "/subscriptions/[parameters('subscriptionId')]/resourceGroups/[parameters('resourceGroupName')]/providers/Microsoft.ApiManagement/service/engineering-thesis-api/apis/Api",
      "type": "apis.azure",
      "apiEndpoint": "https://engineering-thesis-api.azure-api.net/"
    },
    "mssql1": {
      "resourceId": "/subscriptions/[parameters('subscriptionId')]/resourceGroups/[parameters('resourceGroupName')]/providers/Microsoft.Sql/servers/engineering-thesis-dbdbserver/databases/Engineering-thesis-db",
      "type": "mssql.azure",
      "connectionId": "DefaultConnection",
      "secretStore": "AzureAppSettings"
    }
  }
}